[
  {
    "id": 1,
    "name": "布衣",
    "tips": "普普通通的布衣，勉强遮羞吧~",
    "attack": 0,
    "armor": 5,
    "price": 10,
    "type": "B1",
    "strengthen": 0,
    "is_can_strengthen": 0,
    "is_can_update": 1,
    "is_special": 1,
    "belong_monster_id":"1001,",

    "is_can_mixture": 1
  },
  {
    "id": 2,
    "name": "布甲",
    "tips": "和布衣唯一的区别就是，一字之差~",
    "attack": 0,
    "armor": 8,
    "belong_monster_id":"1001,",


    "price": 20,
    "type": "B2",
    "strengthen": 0,
    "is_can_strengthen": 0,
    "is_can_update": 1,
    "is_special": 1,
    "is_can_mixture": 1
  },
  {
    "id": 3,
    "name": "轻盔甲",
    "tips": "入门级铠甲，多多少少像点样子。",
    "attack": 3,
    "armor": 20,
    "price": 100,
    "type": "B3",
    "belong_monster_id":"1001,",


    "strengthen": 0,
    "is_can_strengthen": 0,
    "is_can_update": 1,
    "is_special": 1,
    "is_can_mixture": 1
  },
  {
    "id": 4,
    "name": "重盔甲",
    "tips": "穿上贼拉风的铠甲，就是有点重。",
    "attack": 15,
    "armor": 50,
    "price": 500,
    "type": "B4",
    "belong_monster_id":"1001,",


    "strengthen": 0,
    "is_can_strengthen": 0,
    "is_can_update": 1,
    "is_special": 1,
    "is_can_mixture": 1
  },
  {
    "id": 5,
    "name": "战神甲",
    "tips": "听着名字就知道这是个“狠角色”，干就完了！<br/>可合成为：<font color=\"#7B1FA2\">真·战神甲</font>",
    "attack": 30,
    "armor": 100,
    "price": 3000,
    "type": "B5",
    "belong_monster_id":"1001,",


    "strengthen": 0,
    "is_can_strengthen": 0,
    "is_can_update": 1,
    "is_special": 1,
    "is_can_mixture": 1
  },
  {
    "id": 6,
    "name": "<font color=\"#7B1FA2\">真·战神甲</font>",
    "tips": "合成公式：战神甲+战神令（材料）",
    "attack": 150,
    "armor": 300,
    "price": 2,
    "type": "B6",
    "strengthen": 0,
    "is_can_strengthen": 0,
    "belong_monster_id":"1002,",


    "is_can_update": 1,
    "is_special": 0,
    "strengthen_formula": "[{\"type\":\"E3\"}]",
    "mixture_formula": "[{\"type\":\"B5\"},{\"type\":\"E4\"}]",
    "is_can_mixture": 0
  },
  {
    "id": 7,
    "name": "<font color=\"#FBC02D\">刃甲</font>",
    "tips": "合成公式：重盔甲+双刃+铜矿石",
    "attack": 200,
    "armor": 80,
    "price": 2,
    "type": "B7",
    "belong_monster_id":"1002,",
    "strengthen": 0,
    "is_can_strengthen": 0,
    "is_can_update": 1,
    "is_special": 0,
    "strengthen_formula": "[{\"type\":\"E3\"}]",
    "mixture_formula": "[{\"type\":\"B4\"},{\"type\":\"E2\"},{\"type\":\"A8\"}]",
    "is_can_mixture": 0
  }
]